MANIFEST.in
README.md
requirements.txt
setup.cfg
setup.py
versioneer.py
dmsky/__init__.py
dmsky/_version.py
dmsky/density.py
dmsky/factory.py
dmsky/jcalc.py
dmsky/library.py
dmsky/plotting.py
dmsky/priors.py
dmsky/roster.py
dmsky/skymap.py
dmsky/targets.py
dmsky.egg-info/PKG-INFO
dmsky.egg-info/SOURCES.txt
dmsky.egg-info/dependency_links.txt
dmsky.egg-info/requires.txt
dmsky.egg-info/top_level.txt
dmsky/data/rosters/roster.yaml
dmsky/data/targets/defaults.yaml
dmsky/data/targets/clusters/default.yaml
dmsky/data/targets/dwarfs/ackermann2014.yaml
dmsky/data/targets/dwarfs/albert2017.yaml
dmsky/data/targets/dwarfs/defaults.yaml
dmsky/data/targets/dwarfs/geringer-sameth2015.yaml
dmsky/data/targets/dwarfs/koposov2018.yaml
dmsky/data/targets/dwarfs/martinez2015.yaml
dmsky/data/targets/dwarfs/pace2018.yaml
dmsky/data/targets/galactic/ackermann2012.yaml
dmsky/data/targets/galactic/ackermann2013.yaml
dmsky/data/targets/galactic/defaults.yaml
dmsky/data/targets/galaxies/defaults.yaml
dmsky/data/targets/isotropic/default.yaml
dmsky/file_io/__init__.py
dmsky/file_io/table.py
dmsky/utils/__init__.py
dmsky/utils/coords.py
dmsky/utils/healpix.py
dmsky/utils/speed.py
dmsky/utils/stat_funcs.py
dmsky/utils/tools.py
dmsky/utils/units.py
dmsky/utils/wcs.py